{
  "apiMessage": "This JSON was provided by Springer Nature",
  "query": "keyword:moral AND keyword:economy AND keyword:welfare",
  "result": [
    {
      "total": "10",
      "start": "1",
      "pageLength": "12",
      "recordsDisplayed": "10"
    }
  ],
  "records": [
    {
      "contentType": "Chapter ReferenceWorkEntry",
      "identifier": "doi:10.1057/978-1-349-95189-5_598",
      "language": "en",
      "url": [
        {
          "format": "html",
          "platform": "web",
          "value": "http://link.springer.com/openurl/fulltext?id=doi:10.1057/978-1-349-95189-5_598"
        },
        {
          "format": "",
          "platform": "",
          "value": "http://dx.doi.org/10.1057/978-1-349-95189-5_598"
        }
      ],
      "title": "Edgeworth, Francis Ysidro (1845–1926)",
      "creators": [
        {
          "creator": "Creedy, John"
        }
      ],
      "publicationName": "The New Palgrave Dictionary of Economics",
      "openaccess": "false",
      "doi": "10.1057/978-1-349-95189-5_598",
      "publisher": "Springer",
      "publisherName": "Palgrave Macmillan UK",
      "publicationDate": "2018-01-01",
      "publicationType": "Book",
      "abstract": "Edgeworth was a major figure in the development of neoclassical economics, and one of its most original theorists, making a wide range of lasting contributions. After describing his approach to economics, this article discusses his early work in moral philosophy, which had a strong influence on his economics. His important contribution to the theory of exchange, focusing on indeterminacy and the role of the number of traders, is examined. His later work on monopoly, international trade and taxation are then briefly discussed.",
      "conferenceInfo": [],
      "keyword": [
        "Arbitration",
        "Assumptions",
        "Barter",
        "Bentham, J.",
        "Bickerdike, C.",
        "Bilateral monopoly",
        "Biological analogies",
        "Bootstrap",
        "Butler, J.",
        "Calculus of variations",
        "Coalitions",
        "Collusion",
        "Combinations",
        "Competitive (price-taking) equilibrium",
        "Complements:  substitutes and complements",
        "Conjectural variations",
        "Contract curve",
        "Correlation coefficient",
        "Cournot, A.",
        "Darwin, C.",
        "Deductive method",
        "Determinacy and indeterminacy of exchange",
        "Distributive justice",
        "Duopoly",
        "Edgeworth box",
        "Edgeworth, F.",
        "Egoism",
        "Equilibrium in exchange",
        "Experimental psychology",
        "First fundamental theorem of welfare economics",
        "Giffen good",
        "Harsanyi, J.",
        "Historical School",
        "Hotelling, H.",
        "Idealism",
        "Immiserizing growth",
        "Indeterminacy of contract",
        "Indifference map",
        "Inference",
        "International trade",
        "International values, theory of",
        "Intuitionism",
        "Jevons, W.",
        "Keynes, J. M.",
        "Lagrange multipliers",
        "Laplace, P.",
        "Launhardt, C.",
        "Law of indifference",
        "Marshall, A.",
        "Mathematical economics",
        "Mechanical analogies",
        "Mill, J. S.",
        "Monotonicity",
        "Moral philosophy",
        "Negative income tax",
        "Neoclassical",
        "No-profit entrepreneur",
        "Offer curve",
        "Optimal distribution",
        "Optimal tariffs",
        "Paley A. and M.",
        "’",
        "Partial equilibrium theory",
        "Pearson distributions",
        "Physical sciences",
        "Pigou, A.",
        "Probability",
        "Progressive and regressive taxation",
        "Rate of exchange",
        "Reciprocal demand curve",
        "Recontracting",
        "Royal Statistical Society",
        "Rules of conduct",
        "Sacrifice theory of tax incidence",
        "Saddle point",
        "Schumpeter, J.",
        "Sidgwick, H.",
        "Social contract",
        "Social welfare function",
        "Statistical inference",
        "Substitutes and complements",
        "Tax incidence",
        "Taxation, theory of",
        "Transformations",
        "Utilitarianism",
        "Utility functions",
        "Utility maximization",
        "Vickrey, W.",
        "Walras, L.",
        "B31"
      ],
      "subjects": [
        "Economics",
        "Economics, general",
        "Business Mathematics"
      ],
      "disciplines": [
        {
          "id": "3032",
          "term": "Economics"
        },
        {
          "id": "4463",
          "term": "Business Mathematics"
        }
      ],
      "printIsbn": "978-1-349-95188-8",
      "electronicIsbn": "978-1-349-95189-5",
      "isbn": "978-1-349-95188-8",
      "genre": "OriginalPaper Encyclop(a)edia",
      "onlineDate": "2018-02-15",
      "copyright": "©2018 The Editor(s) (if applicable) and The Author(s)"
    },
    {
      "contentType": "Chapter ReferenceWorkEntry",
      "identifier": "doi:10.1057/978-1-349-95189-5_1588",
      "language": "en",
      "url": [
        {
          "format": "html",
          "platform": "web",
          "value": "http://link.springer.com/openurl/fulltext?id=doi:10.1057/978-1-349-95189-5_1588"
        },
        {
          "format": "",
          "platform": "",
          "value": "http://dx.doi.org/10.1057/978-1-349-95189-5_1588"
        }
      ],
      "title": "Welfare State",
      "creators": [
        {
          "creator": "Lindbeck, Assar"
        }
      ],
      "publicationName": "The New Palgrave Dictionary of Economics",
      "openaccess": "false",
      "doi": "10.1057/978-1-349-95189-5_1588",
      "publisher": "Springer",
      "publisherName": "Palgrave Macmillan UK",
      "publicationDate": "2018-01-01",
      "publicationType": "Book",
      "abstract": "This article starts out with a brief discussion of the historical background, the justifications and the political forces behind the creation of the modern welfare state. It also summarizes its major achievements in terms of economic efficiency and redistribution. The article also tries to identify some major problems of contemporary welfare-state arrangements, distinguishing problems caused by exogenous shocks from those related to endogenous behaviour adjustments by individuals to the welfare state itself. The latter include tax distortions, moral hazard, and endogenous changes in social norms concerning work and benefit dependency.",
      "conferenceInfo": [],
      "keyword": [
        "Advantageous selection",
        "Adverse selection",
        "Aging and retirement",
        "Altruism",
        "Baumol, W.",
        "Birth rates",
        "Child care",
        "Civil society",
        "Dependency",
        "Direct provision vs subsidy",
        "Distribution of income",
        "Early retirement pensions",
        "Education",
        "Employment subsidies",
        "Enlightened self-interest",
        "Family",
        "Free riding",
        "Gini coefficient",
        "Globalization",
        "Health care",
        "Human capital investment",
        "Human services",
        "Immigration",
        "Income effects",
        "Income insurance",
        "Income smoothing",
        "Individualization",
        "Industrialization",
        "Intergenerational contracting",
        "Intergenerational transfers",
        "International trade (theory)",
        "Intra-individual redistribution",
        "Job-security legislation",
        "Labour supply",
        "Labour-Intensive human services",
        "Labour-Market programmes",
        "Leisure",
        "Luxembourg Income Study",
        "Marginal tax rates",
        "Market failure",
        "Moral hazard",
        "Myopia",
        "Non-governmental organizations",
        "Non-profit organizations",
        "Old-age care",
        "Political economy of income redistribution",
        "Preschooling",
        "Productivity growth",
        "Public social spending",
        "Redistribution of income and wealth",
        "Retraining",
        "Risk sharing",
        "Sickness benefits",
        "Social insurance",
        "Social norms",
        "Structural change",
        "Structural unemployment",
        "Substitution effect",
        "Sweden",
        "Tax base",
        "Tax competition",
        "Tax distortions",
        "Tax wedge",
        "Transfer payments",
        "Unemployment benefits",
        "Universal vs. targeted transfers",
        "Urbanization",
        "User fees",
        "Voucher systems",
        "Welfare state",
        "Working poor",
        "H1"
      ],
      "subjects": [
        "Economics",
        "Economics, general",
        "Business Mathematics"
      ],
      "disciplines": [
        {
          "id": "3032",
          "term": "Economics"
        },
        {
          "id": "4463",
          "term": "Business Mathematics"
        }
      ],
      "printIsbn": "978-1-349-95188-8",
      "electronicIsbn": "978-1-349-95189-5",
      "isbn": "978-1-349-95188-8",
      "genre": "OriginalPaper Encyclop(a)edia",
      "onlineDate": "2018-02-15",
      "copyright": "©2018 The Editor(s) (if applicable) and The Author(s)"
    },
    {
      "contentType": "Article",
      "identifier": "doi:10.1057/s41290-016-0022-6",
      "language": "en",
      "url": [
        {
          "format": "html",
          "platform": "web",
          "value": "http://link.springer.com/openurl/fulltext?id=doi:10.1057/s41290-016-0022-6"
        },
        {
          "format": "pdf",
          "platform": "web",
          "value": "http://link.springer.com/openurl/pdf?id=doi:10.1057/s41290-016-0022-6"
        },
        {
          "format": "",
          "platform": "",
          "value": "http://dx.doi.org/10.1057/s41290-016-0022-6"
        }
      ],
      "title": "Work, welfare, and the values of voluntarism: Rethinking Anscombe’s “action under a description” in postwar markets for human subjects",
      "creators": [
        {
          "creator": "Stark, Laura"
        }
      ],
      "publicationName": "American Journal of Cultural Sociology",
      "openaccess": "false",
      "doi": "10.1057/s41290-016-0022-6",
      "publisher": "Springer",
      "publisherName": "Palgrave Macmillan UK",
      "publicationDate": "2017-03-01",
      "publicationType": "Journal",
      "abstract": "This paper documents an exchange for healthy human subjects of medical experiments brokered and carried out by a labor union (The United Mine Workers of America) and the federal government (The US National Institutes of Health). The organizations legally established the exchange in a 1960 contract; jobless people took part in the exchange throughout the decade; and the exchange served as a “prototype” for additional exchanges between NIH and organizations in blue-collar communities. The exchange was successful because the organizations negotiated two “dissonant descriptions” of the same action to manage two different audiences – one legal, one vernacular. The case engages three issues in cultural sociology. First, the episode illustrates how philosopher GEM Anscombe’s concept of “action under a description” solves a puzzle embedded in studies of culture-in-action and offers a way to more systematically study symbolic action. Second, it demonstrates precisely how organizations, paradoxically, use the language of voluntarism to accomplish market goals. Third, it illuminates the terms of engagement with new commodities and markets in the age of biocapital and in doing so helps deepen understandings of moral markets.",
      "conferenceInfo": [],
      "keyword": [
        "Anscombe",
        "inequality",
        "employment",
        "welfare",
        "War on Poverty",
        "volunteer",
        "economy",
        "UMWA",
        "moral markets",
        "labor unions",
        "NIH",
        "human subjects"
      ],
      "subjects": [
        "Social Sciences",
        "Social Sciences, general",
        "Sociology, general",
        "Sociology of Culture",
        "Media Sociology"
      ],
      "disciplines": [
        {
          "id": "2891",
          "term": "Society"
        },
        {
          "id": "2902",
          "term": "Sociology"
        },
        {
          "id": "3111",
          "term": "Sociology of Culture"
        },
        {
          "id": "4351",
          "term": "Media Sociology"
        }
      ],
      "sntsubjects": [
        {
          "id": "4776",
          "term": "Action Theory"
        },
        {
          "id": "8047",
          "term": "Sociology of Work"
        },
        {
          "id": "8037",
          "term": "Communication of Non-Profit Organizations"
        },
        {
          "id": "2891",
          "term": "Society"
        },
        {
          "id": "7332",
          "term": "Sociology of Organizations and Occupations"
        },
        {
          "id": "2902",
          "term": "Sociology"
        }
      ],
      "issn": "2049-7113",
      "eIssn": "2049-7121",
      "volume": "5",
      "number": "1-2",
      "issueType": "Combined",
      "topicalCollection": "",
      "genre": [
        "OriginalPaper",
        "Original Article"
      ],
      "startingPage": "181",
      "endingPage": "224",
      "article-number": "",
      "journalId": "41290",
      "printDate": "2017-03-06",
      "onlineDate": "2017-02-08",
      "coverDate": "2017-03",
      "copyright": "©2017 Macmillan Publishers Ltd"
    },
    {
      "contentType": "Chapter",
      "identifier": "doi:10.1007/978-3-319-52545-7_4",
      "language": "en",
      "url": [
        {
          "format": "html",
          "platform": "web",
          "value": "http://link.springer.com/openurl/fulltext?id=doi:10.1007/978-3-319-52545-7_4"
        },
        {
          "format": "pdf",
          "platform": "web",
          "value": "http://link.springer.com/openurl/pdf?id=doi:10.1007/978-3-319-52545-7_4"
        },
        {
          "format": "",
          "platform": "",
          "value": "http://dx.doi.org/10.1007/978-3-319-52545-7_4"
        }
      ],
      "title": "\n      Public Economy (“Gemeinwirtschaft”) as a Concept of Social Development Policy—Examples of German Authors of the Late 19th Century",
      "creators": [
        {
          "creator": "Schmidt, Karl-Heinz"
        }
      ],
      "bookEditors": [
        {
          "bookEditor": "BACKHAUS, JÜRGEN"
        },
        {
          "bookEditor": "CHALOUPEK, GÜNTHER"
        },
        {
          "bookEditor": "FRAMBACH, HANS A."
        }
      ],
      "publicationName": "On the Economic Significance of the Catholic Social Doctrine",
      "openaccess": "false",
      "doi": "10.1007/978-3-319-52545-7_4",
      "publisher": "Springer",
      "publisherName": "Springer International Publishing",
      "publicationDate": "2017-01-01",
      "publicationType": "Book",
      "abstract": "In Central Europe, especially in Germany, economic and social activities of state-authorities and non-profit organizations are based on long-term traditions in practice and economic thought. During the 19th century state-authorities, private market-institutions, non-profit-organizations and related institutions demonstrated the “three-sector-structure” of the market-economy. The term “Gemeinwirtschaft” was introduced (von Hermann 1924 ) to designate cooperative behavior of actors and institutions. In spite of long-term debates about the definition and effects of “Gemeinwirtschaft” the “floor is open” for further discussion—also in relation to religious documents and declarations by the Churches, including encyclicals by the Pope. Based on this background the paper refers to the long-term development of “Gemeinwirtschaft” and to examples of social development studies during the late 19th century. The examples point out different “driving forces” of social development—firstly individual persons, secondly clubs, unions, cooperatives etc. Schools of economic thought are emphasized demanding new measures of social policy or of a new economic and social system. “Three stars” of development of “public economy” including “Gemeinwirtschaft”—Adolph Wagner, Albert Schäffle and Emil Sax—are considered. Furthermore attempts by the Pope Leo XIII (1878–1903) to solve the conflict between the Catholic Church and the modern State are emphasized. Especially the importance of the encyclical “Rerum Novarum” (1891) is demonstrated. To consider the socio-economic environment the paper also turns to specific authors on social development and “public economy” (F. Hitze and K. Frh. v. Vogelsang on the Catholic side, J. H. v. Wichern and V.A. Huber on the Protestant side). The conclusions refer to the “driving forces” and to the selected authors. The relations between the Churches and the State at the end of the 19th century become apparent as background of social documents and of practical policy but also as attempt to promote a “third way” of economic and social development.",
      "conferenceInfo": [],
      "keyword": [
        "Public economy (Gemeinwirtschaft)",
        "Non-profit-organizations",
        "Social movement",
        "Social reformers",
        "Social question",
        "Moral renovation of people",
        "Church-oriented politicians",
        "Maximization of social welfare",
        "B19",
        "B31",
        "B9",
        "P00",
        "Z12"
      ],
      "subjects": [
        "Economics",
        "Economic History",
        "Social Policy",
        "Cultural Economics",
        "Catholicism"
      ],
      "disciplines": [
        {
          "id": "5858",
          "term": "History of Economic Thought and Methodology"
        },
        {
          "id": "4293",
          "term": "Economic History"
        },
        {
          "id": "7998",
          "term": "Social Policy"
        },
        {
          "id": "4968",
          "term": "Cultural Economics"
        },
        {
          "id": "6219",
          "term": "Catholicism"
        }
      ],
      "sntsubjects": [
        {
          "id": "7967",
          "term": "Social Economy"
        },
        {
          "id": "3911",
          "term": "Public Economics"
        },
        {
          "id": "4293",
          "term": "Economic History"
        },
        {
          "id": "5858",
          "term": "History of Economic Thought and Methodology"
        },
        {
          "id": "4376",
          "term": "Economic Sociology"
        },
        {
          "id": "5359",
          "term": "Socio-Economic Policy"
        }
      ],
      "printIsbn": "978-3-319-52544-0",
      "electronicIsbn": "978-3-319-52545-7",
      "isbn": "978-3-319-52544-0",
      "genre": "OriginalPaper Contributed volume",
      "seriesId": "5902",
      "onlineDate": "2017-04-26",
      "copyright": "©2017 Springer International Publishing AG"
    },
    {
      "contentType": "Chapter",
      "identifier": "doi:10.1057/9781137314154_8",
      "language": "en",
      "url": [
        {
          "format": "html",
          "platform": "web",
          "value": "http://link.springer.com/openurl/fulltext?id=doi:10.1057/9781137314154_8"
        },
        {
          "format": "pdf",
          "platform": "web",
          "value": "http://link.springer.com/openurl/pdf?id=doi:10.1057/9781137314154_8"
        },
        {
          "format": "",
          "platform": "",
          "value": "http://dx.doi.org/10.1057/9781137314154_8"
        }
      ],
      "title": "Comparing Beyond Europe and North America",
      "creators": [
        {
          "creator": "Wong, Joseph"
        }
      ],
      "bookEditors": [
        {
          "bookEditor": "Engeli, Isabelle"
        },
        {
          "bookEditor": "Allison, Christine Rothmayr"
        }
      ],
      "publicationName": "Comparative Policy Studies",
      "openaccess": "false",
      "doi": "10.1057/9781137314154_8",
      "publisher": "Springer",
      "publisherName": "Palgrave Macmillan UK",
      "publicationDate": "2014-01-01",
      "publicationType": "Book",
      "abstract": "The 1982 publication of Chalmers Johnson’s book, MITI and the Japanese Miracle: The Growth of Industrial Policy, 1925 to 1975 , was a watershed moment in comparative policy studies (Johnson, 1982). The book introduced Western readers to the Japanese developmental experience, precisely at the moment when Japan was rivalling the United States in terms of global economic dominance. Johnson’s book provided in-depth analyses of trade, investment, human capital development and strategic industrial policies to grow Japanese enterprises into world-class competitors. His study revealed how Japanese firms were organized and how they were linked to the powerful state. The book also explained how policy decisions in Japan were made in a hierarchical manner, how power and authority over resource allocation decisions were centralized in a meritocratic bureaucracy, and specifically within what Johnson called the state’s ‘pilot agency’, the Ministry of International Trade and Industry (MITI). Finally, Johnson’s book intimated that a hard or strong state was helpful, at least in Japan’s experience, in steering national economic development and continual industrial upgrading.",
      "conferenceInfo": [],
      "keyword": [
        "Welfare State",
        "Industrial Policy",
        "Moral Economy",
        "Social Science Theory",
        "Theoretical Bias"
      ],
      "subjects": [
        "Social Sciences",
        "Social Policy",
        "Public Policy",
        "Comparative Politics",
        "Political Theory",
        "Political Philosophy",
        "Public Administration"
      ],
      "disciplines": [
        {
          "id": "7940",
          "term": "Methodology of Political Science"
        },
        {
          "id": "7998",
          "term": "Social Policy"
        },
        {
          "id": "5173",
          "term": "Public Policy"
        },
        {
          "id": "3932",
          "term": "Comparative Politics"
        },
        {
          "id": "6334",
          "term": "Political Theory"
        },
        {
          "id": "4005",
          "term": "Political Philosophy"
        },
        {
          "id": "7918",
          "term": "Public Administration"
        }
      ],
      "sntsubjects": [
        {
          "id": "5893",
          "term": "History of Japan"
        },
        {
          "id": "7910",
          "term": "Comparative Public Policy"
        },
        {
          "id": "7369",
          "term": "Comparative Social Policy"
        },
        {
          "id": "3932",
          "term": "Comparative Politics"
        },
        {
          "id": "4431",
          "term": "Comparative Literature"
        },
        {
          "id": "4195",
          "term": "Non-Fiction Literature"
        }
      ],
      "printIsbn": "978-1-349-33498-8",
      "electronicIsbn": "978-1-137-31415-4",
      "isbn": "978-1-349-33498-8",
      "genre": "OriginalPaper Monograph",
      "seriesId": "14503",
      "copyright": "©2014 Palgrave Macmillan, a division of Macmillan Publishers Limited"
    },
    {
      "contentType": "Chapter ReferenceWorkEntry",
      "identifier": "doi:10.1057/978-1-349-95121-5_598-2",
      "language": "en",
      "url": [
        {
          "format": "html",
          "platform": "web",
          "value": "http://link.springer.com/openurl/fulltext?id=doi:10.1057/978-1-349-95121-5_598-2"
        },
        {
          "format": "pdf",
          "platform": "web",
          "value": "http://link.springer.com/openurl/pdf?id=doi:10.1057/978-1-349-95121-5_598-2"
        },
        {
          "format": "",
          "platform": "",
          "value": "http://dx.doi.org/10.1057/978-1-349-95121-5_598-2"
        }
      ],
      "title": "Edgeworth, Francis Ysidro (1845–1926)",
      "creators": [
        {
          "creator": "Creedy, John"
        }
      ],
      "publicationName": "The New Palgrave Dictionary of Economics",
      "openaccess": "false",
      "doi": "10.1057/978-1-349-95121-5_598-2",
      "publisher": "Springer",
      "publisherName": "Palgrave Macmillan UK",
      "publicationDate": "2008-01-01",
      "publicationType": "Book",
      "abstract": "Edgeworth was a major figure in the development of neoclassical economics, and one of its most original theorists, making a wide range of lasting contributions. After describing his approach to economics, this article discusses his early work in moral philosophy, which had a strong influence on his economics. His important contribution to the theory of exchange, focusing on indeterminacy and the role of the number of traders, is examined. His later work on monopoly, international trade and taxation are then briefly discussed.",
      "conferenceInfo": [],
      "keyword": [
        "Arbitration",
        "Assumptions",
        "Barter",
        "Bentham, J.",
        "Bickerdike, C.",
        "Bilateral monopoly",
        "Biological analogies",
        "Bootstrap",
        "Butler, J.",
        "Calculus of variations",
        "Coalitions",
        "Collusion",
        "Combinations",
        "Competitive (price-taking) equilibrium",
        "Complements:  substitutes and complements",
        "Conjectural variations",
        "Contract curve",
        "Correlation coefficient",
        "Cournot, A.",
        "Darwin, C.",
        "Deductive method",
        "Determinacy and indeterminacy of exchange",
        "Distributive justice",
        "Duopoly",
        "Edgeworth box",
        "Edgeworth, F.",
        "Egoism",
        "Equilibrium in exchange",
        "Experimental psychology",
        "First fundamental theorem of welfare economics",
        "Giffen good",
        "Harsanyi, J.",
        "Historical School",
        "Hotelling, H.",
        "Idealism",
        "Immiserizing growth",
        "Indeterminacy of contract",
        "Indifference map",
        "Inference",
        "International trade",
        "International values, theory of",
        "Intuitionism",
        "Jevons, W.",
        "Keynes, J. M.",
        "Lagrange multipliers",
        "Laplace, P.",
        "Launhardt, C.",
        "Law of indifference",
        "Marshall, A.",
        "Mathematical economics",
        "Mechanical analogies",
        "Mill, J. S.",
        "Monotonicity",
        "Moral philosophy",
        "Negative income tax",
        "Neoclassical",
        "No-profit entrepreneur",
        "Offer curve",
        "Optimal distribution",
        "Optimal tariffs",
        "Paley A. and M.",
        "\n                        ’\n                    ",
        "Partial equilibrium theory",
        "Pearson distributions",
        "Physical sciences",
        "Pigou, A.",
        "Probability",
        "Progressive and regressive taxation",
        "Rate of exchange",
        "Reciprocal demand curve",
        "Recontracting",
        "Royal Statistical Society",
        "Rules of conduct",
        "Sacrifice theory of tax incidence",
        "Saddle point",
        "Schumpeter, J.",
        "Sidgwick, H.",
        "Social contract",
        "Social welfare function",
        "Statistical inference",
        "Substitutes and complements",
        "Tax incidence",
        "Taxation, theory of",
        "Transformations",
        "Utilitarianism",
        "Utility functions",
        "Utility maximization",
        "Vickrey, W.",
        "Walras, L.",
        "B31"
      ],
      "subjects": [
        "Economics",
        "Economics, general",
        "Business Mathematics"
      ],
      "disciplines": [
        {
          "id": "3032",
          "term": "Economics"
        },
        {
          "id": "4463",
          "term": "Business Mathematics"
        }
      ],
      "sntsubjects": [
        {
          "id": "4731",
          "term": "Philosophy of Economics"
        },
        {
          "id": "5858",
          "term": "History of Economic Thought and Methodology"
        },
        {
          "id": "8267",
          "term": "Intellectual History"
        },
        {
          "id": "8103",
          "term": "Philosophy of the 19th century"
        },
        {
          "id": "4293",
          "term": "Economic History"
        },
        {
          "id": "6600",
          "term": "Literature and Economics"
        }
      ],
      "printIsbn": "",
      "electronicIsbn": "978-1-349-95121-5",
      "isbn": "",
      "genre": "ReviewPaper Dictionary",
      "onlineDate": "2017-03-17",
      "copyright": "©2017 The Editor(s) (if applicable) and The Author(s)"
    },
    {
      "contentType": "Chapter ReferenceWorkEntry",
      "identifier": "doi:10.1057/978-1-349-95121-5_1588-2",
      "language": "en",
      "url": [
        {
          "format": "html",
          "platform": "web",
          "value": "http://link.springer.com/openurl/fulltext?id=doi:10.1057/978-1-349-95121-5_1588-2"
        },
        {
          "format": "pdf",
          "platform": "web",
          "value": "http://link.springer.com/openurl/pdf?id=doi:10.1057/978-1-349-95121-5_1588-2"
        },
        {
          "format": "",
          "platform": "",
          "value": "http://dx.doi.org/10.1057/978-1-349-95121-5_1588-2"
        }
      ],
      "title": "Welfare State",
      "creators": [
        {
          "creator": "Lindbeck, Assar"
        }
      ],
      "publicationName": "The New Palgrave Dictionary of Economics",
      "openaccess": "false",
      "doi": "10.1057/978-1-349-95121-5_1588-2",
      "publisher": "Springer",
      "publisherName": "Palgrave Macmillan UK",
      "publicationDate": "2008-01-01",
      "publicationType": "Book",
      "abstract": "This article starts out with a brief discussion of the historical background, the justifications and the political forces behind the creation of the modern welfare state. It also summarizes its major achievements in terms of economic efficiency and redistribution. The article also tries to identify some major problems of contemporary welfare-state arrangements, distinguishing problems caused by exogenous shocks from those related to endogenous behaviour adjustments by individuals to the welfare state itself. The latter include tax distortions, moral hazard, and endogenous changes in social norms concerning work and benefit dependency.",
      "conferenceInfo": [],
      "keyword": [
        "Advantageous selection",
        "Adverse selection",
        "Aging and retirement",
        "Altruism",
        "Baumol, W.",
        "Birth rates",
        "Child care",
        "Civil society",
        "Dependency",
        "Direct provision vs subsidy",
        "Distribution of income",
        "Early retirement pensions",
        "Education",
        "Employment subsidies",
        "Enlightened self-interest",
        "Family",
        "Free riding",
        "Gini coefficient",
        "Globalization",
        "Health care",
        "Human capital investment",
        "Human services",
        "Immigration",
        "Income effects",
        "Income insurance",
        "Income smoothing",
        "Individualization",
        "Industrialization",
        "Intergenerational contracting",
        "Intergenerational transfers",
        "International trade (theory)",
        "Intra-individual redistribution",
        "Job-security legislation",
        "Labour supply",
        "Labour-Intensive human services",
        "Labour-Market programmes",
        "Leisure",
        "Luxembourg Income Study",
        "Marginal tax rates",
        "Market failure",
        "Moral hazard",
        "Myopia",
        "Non-governmental organizations",
        "Non-profit organizations",
        "Old-age care",
        "Political economy of income redistribution",
        "Preschooling",
        "Productivity growth",
        "Public social spending",
        "Redistribution of income and wealth",
        "Retraining",
        "Risk sharing",
        "Sickness benefits",
        "Social insurance",
        "Social norms",
        "Structural change",
        "Structural unemployment",
        "Substitution effect",
        "Sweden",
        "Tax base",
        "Tax competition",
        "Tax distortions",
        "Tax wedge",
        "Transfer payments",
        "Unemployment benefits",
        "Universal vs. targeted transfers",
        "Urbanization",
        "User fees",
        "Voucher systems",
        "Welfare state",
        "Working poor",
        "H1"
      ],
      "subjects": [
        "Economics",
        "Economics, general",
        "Business Mathematics"
      ],
      "disciplines": [
        {
          "id": "3032",
          "term": "Economics"
        },
        {
          "id": "4463",
          "term": "Business Mathematics"
        }
      ],
      "sntsubjects": [
        {
          "id": "4076",
          "term": "Social Choice and Welfare"
        },
        {
          "id": "7009",
          "term": "Welfare"
        },
        {
          "id": "7155",
          "term": "Social Inequality"
        },
        {
          "id": "7998",
          "term": "Social Policy"
        },
        {
          "id": "7369",
          "term": "Comparative Social Policy"
        },
        {
          "id": "5359",
          "term": "Socio-Economic Policy"
        }
      ],
      "printIsbn": "",
      "electronicIsbn": "978-1-349-95121-5",
      "isbn": "",
      "genre": "ReviewPaper Dictionary",
      "onlineDate": "2017-03-13",
      "copyright": "©2017 The Editor(s) (if applicable) and The Author(s)"
    },
    {
      "contentType": "Article",
      "identifier": "doi:10.1007/s11575-006-0112-8",
      "language": "en",
      "url": [
        {
          "format": "html",
          "platform": "web",
          "value": "http://link.springer.com/openurl/fulltext?id=doi:10.1007/s11575-006-0112-8"
        },
        {
          "format": "pdf",
          "platform": "web",
          "value": "http://link.springer.com/openurl/pdf?id=doi:10.1007/s11575-006-0112-8"
        },
        {
          "format": "",
          "platform": "",
          "value": "http://dx.doi.org/10.1007/s11575-006-0112-8"
        }
      ],
      "title": "English Summaries Vol. 58, No. 3, 2006",
      "publicationName": "KZfSS Kölner Zeitschrift für Soziologie und Sozialpsychologie",
      "openaccess": "false",
      "doi": "10.1007/s11575-006-0112-8",
      "publisher": "Springer",
      "publisherName": "VS Verlag für Sozialwissenschaften",
      "publicationDate": "2006-09-01",
      "publicationType": "Journal",
      "abstract": "",
      "conferenceInfo": [],
      "keyword": [
        "English Summary",
        "Social Assistance",
        "Welfare Recipient",
        "Manual Class",
        "Moral Economy"
      ],
      "subjects": [
        "Social Sciences",
        "Social Sciences, general",
        "Sociology, general",
        "Personality and Social Psychology",
        "Methodology of the Social Sciences",
        "Philosophy of the Social Sciences"
      ],
      "disciplines": [
        {
          "id": "2891",
          "term": "Society"
        },
        {
          "id": "2902",
          "term": "Sociology"
        },
        {
          "id": "4023",
          "term": "Personality and Differential Psychology"
        },
        {
          "id": "8070",
          "term": "Sociology of Migration"
        }
      ],
      "issn": "0023-2653",
      "eIssn": "1861-891X",
      "volume": "58",
      "number": "3",
      "issueType": "Regular",
      "topicalCollection": "",
      "genre": [
        "Abstract"
      ],
      "startingPage": "571",
      "endingPage": "572",
      "article-number": "",
      "journalId": "11577",
      "coverDate": "2006-09",
      "copyright": "©2006 VS Verlag für Sozialwissenschaften/Wiesbaden"
    },
    {
      "contentType": "Article",
      "identifier": "doi:10.1007/s11575-006-0107-5",
      "language": "de",
      "url": [
        {
          "format": "html",
          "platform": "web",
          "value": "http://link.springer.com/openurl/fulltext?id=doi:10.1007/s11575-006-0107-5"
        },
        {
          "format": "pdf",
          "platform": "web",
          "value": "http://link.springer.com/openurl/pdf?id=doi:10.1007/s11575-006-0107-5"
        },
        {
          "format": "",
          "platform": "",
          "value": "http://dx.doi.org/10.1007/s11575-006-0107-5"
        }
      ],
      "title": "Die Gesellschaftliche Akzeptanz der Sozialhilfe",
      "creators": [
        {
          "creator": "Sachweh, Patrick"
        },
        {
          "creator": "Ullrich, Carsten G."
        },
        {
          "creator": "Christoph, Bernhard"
        }
      ],
      "publicationName": "KZfSS Kölner Zeitschrift für Soziologie und Sozialpsychologie",
      "openaccess": "false",
      "doi": "10.1007/s11575-006-0107-5",
      "publisher": "Springer",
      "publisherName": "VS Verlag für Sozialwissenschaften",
      "publicationDate": "2006-09-01",
      "publicationType": "Journal",
      "abstract": "Im vorliegenden Beitrag wird untersucht, auf welche Gründe und Motive sich die Akzeptanz eines sozialpolitischen Minderheitenprogramms wie der Sozialhilfe innerhalb der deutschen Bevölkerung stützt. Hierzu werden auf der Basis eigener Umfragedaten Hypothesen zum Zusammenhang des Eigeninteresses der wohlfahrtsstaatlichen Adressaten an der Sozialhilfe, ihrer Gerechtigkeitsüberzeugungen und ihrer viktimisierenden Wahrnehmungen von Sozialhilfeempfängern mit zwei verschiedenen Indikatoren für die Akzeptanz der Sozialhilfe mittels linearer Regressionsanalysen empirisch überprüft. Ein zentrales Ergebnis ist, dass sich die beobachteten Effekte im Sinne des Konzepts der „Moralökonomie” interpretieren lassen, da sowohl die Gerechtigkeitsüberzeugungen der Adressaten wie auch die Wahrnehmungen der Sozialhilfeempfänger mit den in der Sozialhilfe institutionalisierten normativen Prinzipien korrespondieren. This article examines on which grounds the German population is willing to support a social policy program targeted towards minorities such as social assistance. Using our own survey data and applying linear regression analysis, we test several hypotheses concerning the influence of self-interest, justice- orientations, and victim-blaming attitudes towards welfare recipients on two indicators of support for social assistance. A central finding is that the effects can be interpreted in line with the concept of a “moral economy”, in that the justice orientations of the respondents as well as their attitudes towards welfare recipients correspond with the norms incorporated in the institutional architecture of social assistance.",
      "conferenceInfo": [],
      "keyword": [
        "social assistance",
        "poverty",
        "moral economy",
        "welfare state",
        "Sozialhilfe",
        "Armut",
        "Moralökonomie",
        "Wohlfahrtsstaat"
      ],
      "subjects": [
        "Social Sciences",
        "Social Sciences, general",
        "Sociology, general",
        "Personality and Social Psychology",
        "Methodology of the Social Sciences",
        "Philosophy of the Social Sciences"
      ],
      "disciplines": [
        {
          "id": "2891",
          "term": "Society"
        },
        {
          "id": "2902",
          "term": "Sociology"
        },
        {
          "id": "4023",
          "term": "Personality and Differential Psychology"
        },
        {
          "id": "8070",
          "term": "Sociology of Migration"
        }
      ],
      "sntsubjects": [
        {
          "id": "4076",
          "term": "Social Choice and Welfare"
        },
        {
          "id": "7009",
          "term": "Welfare"
        },
        {
          "id": "7369",
          "term": "Comparative Social Policy"
        },
        {
          "id": "7998",
          "term": "Social Policy"
        },
        {
          "id": "8059",
          "term": "Societal Psychology"
        },
        {
          "id": "7967",
          "term": "Social Economy"
        }
      ],
      "issn": "0023-2653",
      "eIssn": "1861-891X",
      "volume": "58",
      "number": "3",
      "issueType": "Regular",
      "topicalCollection": "",
      "genre": [
        "OriginalPaper"
      ],
      "startingPage": "489",
      "endingPage": "509",
      "article-number": "",
      "journalId": "11577",
      "coverDate": "2006-09",
      "copyright": "©2006 VS Verlag für Sozialwissenschaften/Wiesbaden"
    },
    {
      "contentType": "Chapter",
      "identifier": "doi:10.1007/978-1-349-20786-2_11",
      "language": "en",
      "url": [
        {
          "format": "html",
          "platform": "web",
          "value": "http://link.springer.com/openurl/fulltext?id=doi:10.1007/978-1-349-20786-2_11"
        },
        {
          "format": "pdf",
          "platform": "web",
          "value": "http://link.springer.com/openurl/pdf?id=doi:10.1007/978-1-349-20786-2_11"
        },
        {
          "format": "",
          "platform": "",
          "value": "http://dx.doi.org/10.1007/978-1-349-20786-2_11"
        }
      ],
      "title": "Change and Continuity in History and Sociology: The Case of Industrial Paternalism",
      "creators": [
        {
          "creator": "Bradley, Harriet"
        }
      ],
      "bookEditors": [
        {
          "bookEditor": "Kendrick, Stephen"
        },
        {
          "bookEditor": "Straw, Pat"
        },
        {
          "bookEditor": "McCrone, David"
        }
      ],
      "publicationName": "Interpreting the Past, Understanding the Present",
      "openaccess": "false",
      "doi": "10.1007/978-1-349-20786-2_11",
      "publisher": "Springer",
      "publisherName": "Palgrave Macmillan UK",
      "publicationDate": "1990-01-01",
      "publicationType": "Book",
      "abstract": "To some extent this chapter is a challenge to L. P. Hartley’s dictum, cited above. It is, of course, quite true that people behaved differently in the past and that they acted under different meanings and motivations. This is, in part, what makes the study of history so exciting; at times the historian feels much the same way as a social anthropologist confronted with a new civilisation and its (as yet quite incomprehensible) culture. However, it is also the case that people do things the same in the past. This is not to make claims for the existence of any underlying structure of human motivation or universal meanings-system; it is simply to imply that forms of behaving and thinking are passed on from generation to generation, embedded in the culture and built into the structures of institutions. It is for this reason that the sociologist can enter the terrain of history; and it is for this reason, too, that she must do so if she is to comprehend fully the persistence of these culturally embedded and structurally inbuilt forms of behaviour and thought.",
      "conferenceInfo": [],
      "keyword": [
        "Industrial Relation",
        "Moral Economy",
        "Welfare Provision",
        "Sociological Method",
        "Historical Sociology"
      ],
      "subjects": [
        "Social Sciences",
        "Sociology, general",
        "Methodology of the Social Sciences",
        "Historiography and Method"
      ],
      "disciplines": [
        {
          "id": "2902",
          "term": "Sociology"
        },
        {
          "id": "8039",
          "term": "Sociological Methods"
        },
        {
          "id": "2953",
          "term": "Historiography and Method"
        }
      ],
      "sntsubjects": [
        {
          "id": "7168",
          "term": "Historical Sociology"
        },
        {
          "id": "8223",
          "term": "History of Sociology"
        },
        {
          "id": "4469",
          "term": "Sociological Theory"
        },
        {
          "id": "4304",
          "term": "Social History"
        },
        {
          "id": "5271",
          "term": "Historical Anthropology"
        },
        {
          "id": "8049",
          "term": "Industrial Sociology"
        }
      ],
      "printIsbn": "978-0-333-49371-7",
      "electronicIsbn": "978-1-349-20786-2",
      "isbn": "978-0-333-49371-7",
      "genre": "OriginalPaper Monograph",
      "seriesId": "13976",
      "copyright": "©1990 Palgrave Macmillan, a division of Macmillan Publishers Limited"
    }
  ],
  "facets": [
    {
      "name": "subject",
      "values": [
        {
          "value": "Economics",
          "count": "5"
        },
        {
          "value": "Social Sciences",
          "count": "5"
        },
        {
          "value": "Business Mathematics",
          "count": "4"
        },
        {
          "value": "Economics, general",
          "count": "4"
        },
        {
          "value": "Sociology, general",
          "count": "4"
        },
        {
          "value": "Methodology of the Social Sciences",
          "count": "3"
        },
        {
          "value": "Social Sciences, general",
          "count": "3"
        },
        {
          "value": "Personality and Social Psychology",
          "count": "2"
        },
        {
          "value": "Philosophy of the Social Sciences",
          "count": "2"
        },
        {
          "value": "Social Policy",
          "count": "2"
        },
        {
          "value": "Catholicism",
          "count": "1"
        },
        {
          "value": "Comparative Politics",
          "count": "1"
        },
        {
          "value": "Cultural Economics",
          "count": "1"
        },
        {
          "value": "Economic History",
          "count": "1"
        },
        {
          "value": "Historiography and Method",
          "count": "1"
        },
        {
          "value": "Media Sociology",
          "count": "1"
        },
        {
          "value": "Political Philosophy",
          "count": "1"
        },
        {
          "value": "Political Theory",
          "count": "1"
        },
        {
          "value": "Public Administration",
          "count": "1"
        },
        {
          "value": "Public Policy",
          "count": "1"
        }
      ]
    },
    {
      "name": "keyword",
      "values": [
        {
          "value": "B31",
          "count": "3"
        },
        {
          "value": "Moral Economy",
          "count": "3"
        },
        {
          "value": "Advantageous selection",
          "count": "2"
        },
        {
          "value": "Adverse selection",
          "count": "2"
        },
        {
          "value": "Aging and retirement",
          "count": "2"
        },
        {
          "value": "Altruism",
          "count": "2"
        },
        {
          "value": "Arbitration",
          "count": "2"
        },
        {
          "value": "Assumptions",
          "count": "2"
        },
        {
          "value": "Barter",
          "count": "2"
        },
        {
          "value": "Baumol, W.",
          "count": "2"
        },
        {
          "value": "Bentham, J.",
          "count": "2"
        },
        {
          "value": "Bickerdike, C.",
          "count": "2"
        },
        {
          "value": "Bilateral monopoly",
          "count": "2"
        },
        {
          "value": "Biological analogies",
          "count": "2"
        },
        {
          "value": "Birth rates",
          "count": "2"
        },
        {
          "value": "Bootstrap",
          "count": "2"
        },
        {
          "value": "Butler, J.",
          "count": "2"
        },
        {
          "value": "Calculus of variations",
          "count": "2"
        },
        {
          "value": "Child care",
          "count": "2"
        },
        {
          "value": "Civil society",
          "count": "2"
        }
      ]
    },
    {
      "name": "pub",
      "values": [
        {
          "value": "The New Palgrave Dictionary of Economics",
          "count": "4"
        },
        {
          "value": "KZfSS Kölner Zeitschrift für Soziologie und Sozialpsychologie",
          "count": "2"
        },
        {
          "value": "American Journal of Cultural Sociology",
          "count": "1"
        },
        {
          "value": "Comparative Policy Studies",
          "count": "1"
        },
        {
          "value": "Interpreting the Past, Understanding the Present",
          "count": "1"
        },
        {
          "value": "On the Economic Significance of the Catholic Social Doctrine",
          "count": "1"
        }
      ]
    },
    {
      "name": "year",
      "values": [
        {
          "value": "2018",
          "count": "2"
        },
        {
          "value": "2017",
          "count": "2"
        },
        {
          "value": "2014",
          "count": "1"
        },
        {
          "value": "2008",
          "count": "2"
        },
        {
          "value": "2006",
          "count": "2"
        },
        {
          "value": "1990",
          "count": "1"
        }
      ]
    },
    {
      "name": "country",
      "values": [
        {
          "value": "Germany",
          "count": "2"
        },
        {
          "value": "United States",
          "count": "1"
        }
      ]
    },
    {
      "name": "type",
      "values": [
        {
          "value": "Book",
          "count": "7"
        },
        {
          "value": "Journal",
          "count": "3"
        }
      ]
    }
  ]
}